moduletester/TODO.txt
moduletester/__init__.py
moduletester/config.py
moduletester/exporter.py
moduletester/manager.py
moduletester/model.py
moduletester/python_helpers.py
moduletester/serializer.py
moduletester/data/logo/ModuleTester.svg
moduletester/gui/__init__.py
moduletester/gui/main.py
moduletester/gui/window.py
moduletester/gui/components/__init__.py
moduletester/gui/components/body_component.py
moduletester/gui/components/result_information.py
moduletester/gui/components/status_bar_component.py
moduletester/gui/components/test_information.py
moduletester/gui/components/tool_bar_component.py
moduletester/gui/states/__init__.py
moduletester/gui/states/runner.py
moduletester/gui/states/signals.py
moduletester/gui/states/state_machine.py
moduletester/gui/widgets/__init__.py
moduletester/gui/widgets/cli_widget.py
moduletester/gui/widgets/result_comment.py
moduletester/gui/widgets/result_error_widget.py
moduletester/gui/widgets/result_output_widget.py
moduletester/gui/widgets/result_props_widget.py
moduletester/gui/widgets/tab_image_widget.py
moduletester/gui/widgets/test_description_widget.py
moduletester/gui/widgets/test_list_widget.py
moduletester/gui/widgets/test_prop_widget.py
ModuleTester-0.1.0.dist-info/LICENSE
ModuleTester-0.1.0.dist-info/METADATA
ModuleTester-0.1.0.dist-info/WHEEL
ModuleTester-0.1.0.dist-info/entry_points.txt
ModuleTester-0.1.0.dist-info/top_level.txt
ModuleTester-0.1.0.dist-info/RECORD
