Metadata-Version: 2.1
Name: ModuleTester
Version: 0.1.0
Summary: ModuleTester is a test management software for Python packages
Author-email: Codra <p.raybaut@codra.fr>
License: BSD 3-Clause License
Classifier: Topic :: Software Development :: Libraries :: Python Modules
Classifier: Topic :: Utilities
Classifier: Topic :: Software Development :: User Interfaces
Classifier: Operating System :: MacOS
Classifier: Operating System :: Microsoft :: Windows
Classifier: Operating System :: OS Independent
Classifier: Operating System :: POSIX
Classifier: Operating System :: Unix
Classifier: Programming Language :: Python :: 3.8
Classifier: Programming Language :: Python :: 3.9
Classifier: Programming Language :: Python :: 3.10
Classifier: Programming Language :: Python :: 3.11
Classifier: Programming Language :: Python :: 3.12
Requires-Python: <4,>=3.8
License-File: LICENSE
Requires-Dist: guidata >=3.1
Requires-Dist: QtPy >=1.9
Requires-Dist: beautifulsoup4
Provides-Extra: dev
Requires-Dist: black ; extra == 'dev'
Requires-Dist: isort ; extra == 'dev'
Requires-Dist: pylint ; extra == 'dev'
Requires-Dist: Coverage ; extra == 'dev'
Provides-Extra: doc
Requires-Dist: PyQt5 ; extra == 'doc'
Requires-Dist: sphinx >6 ; extra == 'doc'
Requires-Dist: pydata-sphinx-theme ; extra == 'doc'
